SSVEPAnalysisToolbox/__init__.py
SSVEPAnalysisToolbox/algorithms/__init__.py
SSVEPAnalysisToolbox/algorithms/basemodel.py
SSVEPAnalysisToolbox/algorithms/cca.py
SSVEPAnalysisToolbox/algorithms/lsframework.py
SSVEPAnalysisToolbox/algorithms/ms_msetcca_r_1.py
SSVEPAnalysisToolbox/algorithms/ms_msetcca_r_2.py
SSVEPAnalysisToolbox/algorithms/ms_msetcca_r_3.py
SSVEPAnalysisToolbox/algorithms/ms_trca_r_1.py
SSVEPAnalysisToolbox/algorithms/ms_trca_r_2.py
SSVEPAnalysisToolbox/algorithms/tdca.py
SSVEPAnalysisToolbox/algorithms/trca.py
SSVEPAnalysisToolbox/algorithms/utils.py
SSVEPAnalysisToolbox/algorithms/utils_ls.py
SSVEPAnalysisToolbox/datasets/__init__.py
SSVEPAnalysisToolbox/datasets/basedataset.py
SSVEPAnalysisToolbox/datasets/benchmarkdataset.py
SSVEPAnalysisToolbox/datasets/betadataset.py
SSVEPAnalysisToolbox/datasets/eldbetadataset.py
SSVEPAnalysisToolbox/datasets/nakanishidataset.py
SSVEPAnalysisToolbox/datasets/openbmidataset.py
SSVEPAnalysisToolbox/datasets/subjectinfo.py
SSVEPAnalysisToolbox/datasets/wearabledataset.py
SSVEPAnalysisToolbox/evaluator/__init__.py
SSVEPAnalysisToolbox/evaluator/baseevaluator.py
SSVEPAnalysisToolbox/evaluator/performance.py
SSVEPAnalysisToolbox/evaluator/plot.py
SSVEPAnalysisToolbox/utils/__init__.py
SSVEPAnalysisToolbox/utils/algsupport.py
SSVEPAnalysisToolbox/utils/benchmarkpreprocess.py
SSVEPAnalysisToolbox/utils/download.py
SSVEPAnalysisToolbox/utils/io.py
SSVEPAnalysisToolbox/utils/nakanishipreprocess.py
SSVEPAnalysisToolbox/utils/openbmipreprocess.py
SSVEPAnalysisToolbox/utils/wearablepreprocess.py
SSVEPAnalysisToolbox-0.0.5.dist-info/METADATA
SSVEPAnalysisToolbox-0.0.5.dist-info/WHEEL
SSVEPAnalysisToolbox-0.0.5.dist-info/top_level.txt
SSVEPAnalysisToolbox-0.0.5.dist-info/RECORD
