Metadata-Version: 2.1
Name: SSVEPAnalysisToolbox
Version: 0.0.5
Summary: Python package for SSVEP datasets and algorithms
Home-page: https://github.com/pikipity/SSVEP-Analysis-Toolbox
Author: Ze Wang
Author-email: pikipityw@gmail.com
Classifier: Programming Language :: Python :: 3.9
Classifier: Operating System :: OS Independent
Requires-Python: >=3.9
Requires-Dist: numpy <=1.23,>1.0
Requires-Dist: scipy <=1.13,>1.0
Requires-Dist: py7zr <=0.21
Requires-Dist: pooch <=1.8,>1.0
Requires-Dist: joblib <=1.4,>1.0
Requires-Dist: matplotlib <=3.8,>3.0
Requires-Dist: tqdm <=4.66,>4.0
Requires-Dist: scikit-learn <=1.3,>1.0
Requires-Dist: mat73 <=1.0
